CHANGES.txt
README.txt
bootstrap.py
buildout.cfg
setup.py
src/z3c/__init__.py
src/z3c.i18n.egg-info/PKG-INFO
src/z3c.i18n.egg-info/SOURCES.txt
src/z3c.i18n.egg-info/dependency_links.txt
src/z3c.i18n.egg-info/namespace_packages.txt
src/z3c.i18n.egg-info/not-zip-safe
src/z3c.i18n.egg-info/requires.txt
src/z3c.i18n.egg-info/top_level.txt
src/z3c/i18n/README.txt
src/z3c/i18n/__init__.py
src/z3c/i18n/configure.zcml
src/z3c/i18n/iso.py
src/z3c/i18n/tests.py